examples/__init__.py
examples/liwc.py
liwc/__init__.py
liwc/liwc.py
liwc/test_liwc.py
liwc_text_analysis-1.0.2.dist-info/LICENSE
liwc_text_analysis-1.0.2.dist-info/METADATA
liwc_text_analysis-1.0.2.dist-info/WHEEL
liwc_text_analysis-1.0.2.dist-info/top_level.txt
liwc_text_analysis-1.0.2.dist-info/RECORD
