Metadata-Version: 2.1
Name: liwc-text-analysis
Version: 1.0.2
Summary: A python package for the Linguistic Inquiry and Word Count (LIWC) dictionary.
Home-page: https://github.com/evanll/liwc-text-analysis-python
Author: Evan Lalopoulos
Author-email: evan.lalopoulos.2017@my.bristol.ac.uk
License: UNKNOWN
Platform: UNKNOWN
Classifier: Programming Language :: Python :: 3
Classifier: Operating System :: OS Independent
Requires-Python: >=3.6
Requires-Dist: atomicwrites (==1.3.0)
Requires-Dist: attrs (==19.1.0)
Requires-Dist: importlib-metadata (==0.19)
Requires-Dist: more-itertools (==7.2.0)
Requires-Dist: packaging (==19.1)
Requires-Dist: pluggy (==0.12.0)
Requires-Dist: py (==1.8.0)
Requires-Dist: pyparsing (==2.4.2)
Requires-Dist: pytest (==5.1.2)
Requires-Dist: six (==1.12.0)
Requires-Dist: wcwidth (==0.1.7)
Requires-Dist: zipp (==0.6.0)
